jupyter_phoenix_proxy/__init__.py
jupyter_phoenix_proxy/icons/phoenix.svg
jupyter_phoenix_proxy-1.0.0.dist-info/METADATA
jupyter_phoenix_proxy-1.0.0.dist-info/WHEEL
jupyter_phoenix_proxy-1.0.0.dist-info/entry_points.txt
jupyter_phoenix_proxy-1.0.0.dist-info/top_level.txt
jupyter_phoenix_proxy-1.0.0.dist-info/RECORD
