Metadata-Version: 2.4
Name: jupyter-phoenix-proxy
Version: 1.0.0
Summary: Jupyter server proxy for Arize Phoenix
Author-email: LiZongfeng <lzf940629@vip.qq.com>
Maintainer-email: LiZongfeng <lzf940629@vip.qq.com>
License-Expression: MIT
Project-URL: Repository, https://cnb.cool/lzf.ai/jupyter-phoenix-proxy
Keywords: jupyter,jupyterlab,jupyterlab-extension,jupyter-server-proxy
Classifier: Development Status :: 4 - Beta
Classifier: Programming Language :: Python
Classifier: Programming Language :: Python :: 3
Classifier: Framework :: Jupyter
Classifier: Framework :: Jupyter :: JupyterLab
Classifier: Framework :: Jupyter :: JupyterLab :: Extensions
Requires-Python: <3.14,>=3.10
Requires-Dist: arize-phoenix>=12.28.1
Requires-Dist: jupyter-server-proxy>=4.4.0
